{
  "allChords": [
    "Am",
    "C",
    "F",
    "G",
    "Ab",
    "Bb",
    "Gm",
    "Cm"
  ],
  "artist": "Gwen Stefani",
  "fullName": "4 In The Morning - Gwen Stefani",
  "songId": "4_in_the_morning-gwen_stefani",
  "lines": [
    {
      "label": "Verse 1:"
    },
    {
      "className": "chordLyricLine",
      "chordLyricPairs": [
        {
          "chord": "Am",
          "lyric": "Wakin up to find ano",
          "overLyric": true
        },
        {
          "chord": "C",
          "lyric": "ther day",
          "overLyric": true
        }
      ]
    },
    {
      "className": "chordLyricLine",
      "chordLyricPairs": [
        {
          "chord": "F",
          "lyric": "The moon got lost again la",
          "overLyric": true
        },
        {
          "chord": "C",
          "lyric": "st night",
          "overLyric": true
        }
      ]
    },
    {
      "className": "chordLyricLine",
      "chordLyricPairs": [
        {
          "chord": "Am",
          "lyric": "But now the sun has finally ha",
          "overLyric": true
        },
        {
          "chord": "C",
          "lyric": "d its say",
          "overLyric": true
        }
      ]
    },
    {
      "className": "chordLyricLine",
      "chordLyricPairs": [
        {
          "chord": "F",
          "lyric": "I guess I feel alright  ",
          "overLyric": true
        },
        {
          "chord": "C",
          "lyric": ""
        }
      ]
    },
    {
      "className": "chordLyricLine",
      "chordLyricPairs": [
        {
          "chord": null,
          "lyric": "But it ",
          "overLyric": true
        },
        {
          "chord": "F",
          "lyric": "hurts when I think, when I let it sink ",
          "overLyric": true
        },
        {
          "chord": "Am",
          "lyric": "in",
          "overLyric": true
        }
      ]
    },
    {
      "className": "chordLyricLine",
      "chordLyricPairs": [
        {
          "chord": null,
          "lyric": "It’s all over ",
          "overLyric": true
        },
        {
          "chord": "G",
          "lyric": "me",
          "overLyric": true
        }
      ]
    },
    {
      "className": "chordLyricLine",
      "chordLyricPairs": [
        {
          "chord": null,
          "lyric": "I know you’re ",
          "overLyric": true
        },
        {
          "chord": "F",
          "lyric": "here, in the dark",
          "overLyric": true
        }
      ]
    },
    {
      "className": "chordLyricLine",
      "chordLyricPairs": [
        {
          "chord": null,
          "lyric": "I’m watchin' you s",
          "overLyric": true
        },
        {
          "chord": "C",
          "lyric": "leep, it hurts a lot",
          "overLyric": true
        },
        {
          "chord": "G",
          "lyric": ""
        }
      ]
    },
    {
      "label": "Chorus:"
    },
    {
      "className": "chordLyricLine",
      "chordLyricPairs": [
        {
          "chord": null,
          "lyric": "And ",
          "overLyric": true
        },
        {
          "chord": "Ab",
          "lyric": "all I ",
          "overLyric": true
        },
        {
          "chord": "Bb",
          "lyric": "know is you’ve ",
          "overLyric": true
        },
        {
          "chord": "Gm",
          "lyric": "got to give me ",
          "overLyric": true
        },
        {
          "chord": "Cm",
          "lyric": "everything",
          "overLyric": true
        }
      ]
    },
    {
      "className": "chordLyricLine",
      "chordLyricPairs": [
        {
          "chord": null,
          "lyric": "And ",
          "overLyric": true
        },
        {
          "chord": "Ab",
          "lyric": "nothing ",
          "overLyric": true
        },
        {
          "chord": "Bb",
          "lyric": "less, 'cause you ",
          "overLyric": true
        },
        {
          "chord": "Gm",
          "lyric": "know I’d give you ",
          "overLyric": true
        },
        {
          "chord": "Cm",
          "lyric": "all of me",
          "overLyric": true
        }
      ]
    },
    {
      "className": "chordLyricLine",
      "chordLyricPairs": [
        {
          "chord": null,
          "lyric": "I’d give you ",
          "overLyric": true
        },
        {
          "chord": "Ab",
          "lyric": "everything that I am",
          "overLyric": true
        }
      ]
    },
    {
      "className": "chordLyricLine",
      "chordLyricPairs": [
        {
          "chord": null,
          "lyric": "I’m handin over ",
          "overLyric": true
        },
        {
          "chord": "Bb",
          "lyric": "everything that I’ve got",
          "overLyric": true
        }
      ]
    },
    {
      "className": "chordLyricLine",
      "chordLyricPairs": [
        {
          "chord": null,
          "lyric": "Cause I wanna ",
          "overLyric": true
        },
        {
          "chord": "Gm",
          "lyric": "have a really true love",
          "overLyric": true
        }
      ]
    },
    {
      "className": "chordLyricLine",
      "chordLyricPairs": [
        {
          "chord": null,
          "lyric": "Don’t ever wanna ",
          "overLyric": true
        },
        {
          "chord": "Cm",
          "lyric": "have to go and give you up",
          "overLyric": true
        }
      ]
    },
    {
      "className": "chordLyricLine",
      "chordLyricPairs": [
        {
          "chord": null,
          "lyric": "Stay up till ",
          "overLyric": true
        },
        {
          "chord": "Ab",
          "lyric": "four in the morning and the tears are pouring",
          "overLyric": true
        }
      ]
    },
    {
      "className": "chordLyricLine",
      "chordLyricPairs": [
        {
          "chord": null,
          "lyric": "And I ",
          "overLyric": true
        },
        {
          "chord": "Bb",
          "lyric": "wanna make it worth the fight",
          "overLyric": true
        }
      ]
    },
    {
      "className": "chordLyricLine",
      "chordLyricPairs": [
        {
          "chord": null,
          "lyric": "But what have we been ",
          "overLyric": true
        },
        {
          "chord": "Gm",
          "lyric": "doing for all this time",
          "overLyric": true
        }
      ]
    },
    {
      "className": "chordLyricLine",
      "chordLyricPairs": [
        {
          "chord": null,
          "lyric": "Baby if we’re ",
          "overLyric": true
        },
        {
          "chord": "Cm",
          "lyric": "gonna do it come and do it right",
          "overLyric": true
        }
      ]
    },
    {
      "label": "Verse 2:"
    },
    {
      "className": "chordLyricLine",
      "chordLyricPairs": [
        {
          "chord": "Am",
          "lyric": "  All I wanted was to ",
          "overLyric": true
        },
        {
          "chord": "C",
          "lyric": "know I'm safe",
          "overLyric": true
        }
      ]
    },
    {
      "className": "chordLyricLine",
      "chordLyricPairs": [
        {
          "chord": "F",
          "lyric": " Don’t wanna lose the love I "
        },
        {
          "chord": "C",
          "lyric": "found",
          "overLyric": true
        }
      ]
    },
    {
      "className": "chordLyricLine",
      "chordLyricPairs": [
        {
          "chord": "Am",
          "lyric": "  Remember when you said that ",
          "overLyric": true
        },
        {
          "chord": "C",
          "lyric": "you would change",
          "overLyric": true
        }
      ]
    },
    {
      "className": "chordLyricLine",
      "chordLyricPairs": [
        {
          "chord": "F",
          "lyric": " Don’t let me down"
        },
        {
          "chord": "C",
          "lyric": ""
        }
      ]
    },
    {
      "className": "chordLyricLine",
      "chordLyricPairs": [
        {
          "chord": null,
          "lyric": "It’s not ",
          "overLyric": true
        },
        {
          "chord": "F",
          "lyric": "fair, how you are",
          "overLyric": true
        }
      ]
    },
    {
      "className": "chordLyricLine",
      "chordLyricPairs": [
        {
          "chord": null,
          "lyric": "I can’t be com",
          "overLyric": true
        },
        {
          "chord": "C",
          "lyric": "plete, can you give me more",
          "overLyric": true
        },
        {
          "chord": "G",
          "lyric": ""
        }
      ]
    },
    {
      "label": "Chorus:"
    },
    {
      "className": "chordLyricLine",
      "chordLyricPairs": [
        {
          "chord": null,
          "lyric": "And ",
          "overLyric": true
        },
        {
          "chord": "Ab",
          "lyric": "all I ",
          "overLyric": true
        },
        {
          "chord": "Bb",
          "lyric": "know is you’ve ",
          "overLyric": true
        },
        {
          "chord": "Gm",
          "lyric": "got to give me ",
          "overLyric": true
        },
        {
          "chord": "Cm",
          "lyric": "everything",
          "overLyric": true
        }
      ]
    },
    {
      "className": "chordLyricLine",
      "chordLyricPairs": [
        {
          "chord": null,
          "lyric": "And ",
          "overLyric": true
        },
        {
          "chord": "Ab",
          "lyric": "nothing ",
          "overLyric": true
        },
        {
          "chord": "Bb",
          "lyric": "less, 'cause you ",
          "overLyric": true
        },
        {
          "chord": "Gm",
          "lyric": "know I’d give you ",
          "overLyric": true
        },
        {
          "chord": "Cm",
          "lyric": "all of me",
          "overLyric": true
        }
      ]
    },
    {
      "className": "chordLyricLine",
      "chordLyricPairs": [
        {
          "chord": null,
          "lyric": "I’d give you ",
          "overLyric": true
        },
        {
          "chord": "Ab",
          "lyric": "everything that I am",
          "overLyric": true
        }
      ]
    },
    {
      "className": "chordLyricLine",
      "chordLyricPairs": [
        {
          "chord": null,
          "lyric": "I’m handin over ",
          "overLyric": true
        },
        {
          "chord": "Bb",
          "lyric": "everything that I’ve got",
          "overLyric": true
        }
      ]
    },
    {
      "className": "chordLyricLine",
      "chordLyricPairs": [
        {
          "chord": null,
          "lyric": "Cause I wanna ",
          "overLyric": true
        },
        {
          "chord": "Gm",
          "lyric": "have a really true love",
          "overLyric": true
        }
      ]
    },
    {
      "className": "chordLyricLine",
      "chordLyricPairs": [
        {
          "chord": null,
          "lyric": "Don’t ever wanna ",
          "overLyric": true
        },
        {
          "chord": "Cm",
          "lyric": "have to go and give you up",
          "overLyric": true
        }
      ]
    },
    {
      "className": "chordLyricLine",
      "chordLyricPairs": [
        {
          "chord": null,
          "lyric": "Stay up till ",
          "overLyric": true
        },
        {
          "chord": "Ab",
          "lyric": "four in the morning and the tears are pouring",
          "overLyric": true
        }
      ]
    },
    {
      "className": "chordLyricLine",
      "chordLyricPairs": [
        {
          "chord": null,
          "lyric": "And I ",
          "overLyric": true
        },
        {
          "chord": "Bb",
          "lyric": "wanna make it worth the fight",
          "overLyric": true
        }
      ]
    },
    {
      "className": "chordLyricLine",
      "chordLyricPairs": [
        {
          "chord": null,
          "lyric": "But what have we been ",
          "overLyric": true
        },
        {
          "chord": "Gm",
          "lyric": "doing for all this time",
          "overLyric": true
        }
      ]
    },
    {
      "className": "chordLyricLine",
      "chordLyricPairs": [
        {
          "chord": null,
          "lyric": "Baby if we’re ",
          "overLyric": true
        },
        {
          "chord": "Cm",
          "lyric": "gonna do it come and do it right",
          "overLyric": true
        }
      ]
    },
    {
      "label": "Bridge:"
    },
    {
      "className": "chordLyricLine",
      "chordLyricPairs": [
        {
          "chord": "Am",
          "lyric": "Oh please, you know what I need",
          "overLyric": true
        }
      ]
    },
    {
      "className": "chordLyricLine",
      "chordLyricPairs": [
        {
          "chord": "F",
          "lyric": "Save all your lovin for me",
          "overLyric": true
        }
      ]
    },
    {
      "className": "chordLyricLine",
      "chordLyricPairs": [
        {
          "chord": null,
          "lyric": "We ",
          "overLyric": true
        },
        {
          "chord": "Am",
          "lyric": "can’t escape the love",
          "overLyric": true
        }
      ]
    },
    {
      "className": "chordLyricLine",
      "chordLyricPairs": [
        {
          "chord": null,
          "lyric": "With ",
          "overLyric": true
        },
        {
          "chord": "F",
          "lyric": "everything that you have",
          "overLyric": true
        }
      ]
    },
    {
      "label": "Chorus:"
    },
    {
      "className": "chordLyricLine",
      "chordLyricPairs": [
        {
          "chord": null,
          "lyric": "And ",
          "overLyric": true
        },
        {
          "chord": "Ab",
          "lyric": "all I ",
          "overLyric": true
        },
        {
          "chord": "Bb",
          "lyric": "know is you’ve ",
          "overLyric": true
        },
        {
          "chord": "Gm",
          "lyric": "got to give me ",
          "overLyric": true
        },
        {
          "chord": "Cm",
          "lyric": "everything",
          "overLyric": true
        }
      ]
    },
    {
      "className": "chordLyricLine",
      "chordLyricPairs": [
        {
          "chord": null,
          "lyric": "And ",
          "overLyric": true
        },
        {
          "chord": "Ab",
          "lyric": "nothing ",
          "overLyric": true
        },
        {
          "chord": "Bb",
          "lyric": "less, 'cause you ",
          "overLyric": true
        },
        {
          "chord": "Gm",
          "lyric": "know I’d give you ",
          "overLyric": true
        },
        {
          "chord": "Cm",
          "lyric": "all of me",
          "overLyric": true
        }
      ]
    },
    {
      "className": "chordLyricLine",
      "chordLyricPairs": [
        {
          "chord": null,
          "lyric": "I’d give you ",
          "overLyric": true
        },
        {
          "chord": "Ab",
          "lyric": "everything that I am",
          "overLyric": true
        }
      ]
    },
    {
      "className": "chordLyricLine",
      "chordLyricPairs": [
        {
          "chord": null,
          "lyric": "I’m handin over ",
          "overLyric": true
        },
        {
          "chord": "Bb",
          "lyric": "everything that I’ve got",
          "overLyric": true
        }
      ]
    },
    {
      "className": "chordLyricLine",
      "chordLyricPairs": [
        {
          "chord": null,
          "lyric": "Cause I wanna ",
          "overLyric": true
        },
        {
          "chord": "Gm",
          "lyric": "have a really true love",
          "overLyric": true
        }
      ]
    },
    {
      "className": "chordLyricLine",
      "chordLyricPairs": [
        {
          "chord": null,
          "lyric": "Don’t ever wanna ",
          "overLyric": true
        },
        {
          "chord": "Cm",
          "lyric": "have to go and give you up",
          "overLyric": true
        }
      ]
    },
    {
      "className": "chordLyricLine",
      "chordLyricPairs": [
        {
          "chord": null,
          "lyric": "Stay up till ",
          "overLyric": true
        },
        {
          "chord": "Ab",
          "lyric": "four in the morning and the tears are pouring",
          "overLyric": true
        }
      ]
    },
    {
      "className": "chordLyricLine",
      "chordLyricPairs": [
        {
          "chord": null,
          "lyric": "And I ",
          "overLyric": true
        },
        {
          "chord": "Bb",
          "lyric": "wanna make it worth the fight",
          "overLyric": true
        }
      ]
    },
    {
      "className": "chordLyricLine",
      "chordLyricPairs": [
        {
          "chord": null,
          "lyric": "But what have we been ",
          "overLyric": true
        },
        {
          "chord": "Gm",
          "lyric": "doing for all this time",
          "overLyric": true
        }
      ]
    },
    {
      "className": "chordLyricLine",
      "chordLyricPairs": [
        {
          "chord": null,
          "lyric": "Baby if we’re ",
          "overLyric": true
        },
        {
          "chord": "Cm",
          "lyric": "gonna do it come and do it right",
          "overLyric": true
        }
      ]
    }
  ],
  "title": "4 In The Morning",
  "url": "/song/gwen_stefani/4_in_the_morning"
}