{
  "allChords": [
    "Bm",
    "F#",
    "G",
    "D",
    "A#dim",
    "F#7",
    "G7",
    "Em7",
    "Em",
    "Em6"
  ],
  "artist": "Hamilton",
  "fullName": "Alexander Hamilton - Hamilton",
  "songId": "alexander_hamilton - hamilton",
  "lines": [
    {
      "label": "[BURR]"
    },
    {
      "className": "chordLyricLine",
      "chordLyricPairs": [
        {
          "chord": null,
          "lyric": "How does a ",
          "overLyric": true
        },
        {
          "chord": "Bm",
          "lyric": "bastard, orphan, son of a whore and a",
          "overLyric": true
        }
      ]
    },
    {
      "className": "chordLyricLine",
      "chordLyricPairs": [
        {
          "chord": "F#",
          "lyric": "Scotsman, dropped in the middle of a",
          "overLyric": true
        }
      ]
    },
    {
      "className": "chordLyricLine",
      "chordLyricPairs": [
        {
          "chord": null,
          "lyric": "Forgotten ",
          "overLyric": true
        },
        {
          "chord": "G",
          "lyric": "spot in the Caribbean by providence",
          "overLyric": true
        }
      ]
    },
    {
      "className": "chordLyricLine",
      "chordLyricPairs": [
        {
          "chord": null,
          "lyric": "Impoverished, in ",
          "overLyric": true
        },
        {
          "chord": "D",
          "lyric": "squalor",
          "overLyric": true
        }
      ]
    },
    {
      "className": "chordLyricLine",
      "chordLyricPairs": [
        {
          "chord": null,
          "lyric": "Grow up to be a ",
          "overLyric": true
        },
        {
          "chord": "A#dim",
          "lyric": "hero and a scholar?",
          "overLyric": true
        }
      ]
    },
    {
      "label": "[LAURENS]"
    },
    {
      "className": "chordLyricLine",
      "chordLyricPairs": [
        {
          "chord": null,
          "lyric": "The ",
          "overLyric": true
        },
        {
          "chord": "Bm",
          "lyric": "ten-dollar founding father without a father",
          "overLyric": true
        }
      ]
    },
    {
      "className": "chordLyricLine",
      "chordLyricPairs": [
        {
          "chord": null,
          "lyric": "Got a ",
          "overLyric": true
        },
        {
          "chord": "F#",
          "lyric": "lot farther by working a lot harder",
          "overLyric": true
        }
      ]
    },
    {
      "className": "chordLyricLine",
      "chordLyricPairs": [
        {
          "chord": null,
          "lyric": "By being a ",
          "overLyric": true
        },
        {
          "chord": "G",
          "lyric": "lot smarter",
          "overLyric": true
        }
      ]
    },
    {
      "className": "line",
      "chordLyricPairs": [
        {
          "chord": null,
          "lyric": "By being a self-starter",
          "overLyric": true
        }
      ]
    },
    {
      "className": "chordLyricLine",
      "chordLyricPairs": [
        {
          "chord": null,
          "lyric": "By fourteen,",
          "overLyric": true
        },
        {
          "chord": "D",
          "lyric": " they placed him in charge ",
          "overLyric": true
        },
        {
          "chord": "A#dim",
          "lyric": "of a trading charter",
          "overLyric": true
        }
      ]
    },
    {
      "label": "[JEFFERSON]"
    },
    {
      "className": "chordLyricLine",
      "chordLyricPairs": [
        {
          "chord": null,
          "lyric": "And e",
          "overLyric": true
        },
        {
          "chord": "Bm",
          "lyric": "very day while slaves were being slaughtered and carted",
          "overLyric": true
        }
      ]
    },
    {
      "className": "chordLyricLine",
      "chordLyricPairs": [
        {
          "chord": null,
          "lyric": "Awa",
          "overLyric": true
        },
        {
          "chord": "F#",
          "lyric": "y across the waves, he struggled and kept his guard up",
          "overLyric": true
        }
      ]
    },
    {
      "className": "chordLyricLine",
      "chordLyricPairs": [
        {
          "chord": null,
          "lyric": "In",
          "overLyric": true
        },
        {
          "chord": "G",
          "lyric": "side he was longing for something to be a part of",
          "overLyric": true
        }
      ]
    },
    {
      "className": "chordLyricLine",
      "chordLyricPairs": [
        {
          "chord": null,
          "lyric": "The brot",
          "overLyric": true
        },
        {
          "chord": "D",
          "lyric": "her was ready to beg, ",
          "overLyric": true
        },
        {
          "chord": "A#dim",
          "lyric": "steal, borrow, or barter",
          "overLyric": true
        }
      ]
    },
    {
      "label": "[MADISON]"
    },
    {
      "className": "chordLyricLine",
      "chordLyricPairs": [
        {
          "chord": null,
          "lyric": "Then a ",
          "overLyric": true
        },
        {
          "chord": "Bm",
          "lyric": "hurricane came, and devastation reigned",
          "overLyric": true
        }
      ]
    },
    {
      "className": "chordLyricLine",
      "chordLyricPairs": [
        {
          "chord": null,
          "lyric": "Our ma",
          "overLyric": true
        },
        {
          "chord": "F#",
          "lyric": "n saw his future drip, dripping down the drain",
          "overLyric": true
        }
      ]
    },
    {
      "className": "chordLyricLine",
      "chordLyricPairs": [
        {
          "chord": null,
          "lyric": "Put a ",
          "overLyric": true
        },
        {
          "chord": "G",
          "lyric": "pencil to his temple, connected it to his brain",
          "overLyric": true
        }
      ]
    },
    {
      "className": "chordLyricLine",
      "chordLyricPairs": [
        {
          "chord": null,
          "lyric": "And he ",
          "overLyric": true
        },
        {
          "chord": "D",
          "lyric": "wrote his first refrain, a ",
          "overLyric": true
        },
        {
          "chord": "F#",
          "lyric": "testament to his pain",
          "overLyric": true
        }
      ]
    },
    {
      "label": "[BURR]"
    },
    {
      "className": "chordLyricLine",
      "chordLyricPairs": [
        {
          "chord": null,
          "lyric": "Well the w",
          "overLyric": true
        },
        {
          "chord": "Bm",
          "lyric": "ord got around, they said, \"This kid is insane, man\"",
          "overLyric": true
        }
      ]
    },
    {
      "className": "chordLyricLine",
      "chordLyricPairs": [
        {
          "chord": "F#",
          "lyric": "Took up a collection just to send him to the mainland",
          "overLyric": true
        }
      ]
    },
    {
      "className": "chordLyricLine",
      "chordLyricPairs": [
        {
          "chord": "G",
          "lyric": "\"Get your education, don't forget from whence you came",
          "overLyric": true
        }
      ]
    },
    {
      "className": "chordLyricLine",
      "chordLyricPairs": [
        {
          "chord": null,
          "lyric": "and the wo",
          "overLyric": true
        },
        {
          "chord": "D",
          "lyric": "rld is gonna know your ",
          "overLyric": true
        },
        {
          "chord": "F#7",
          "lyric": "name. What's your name, man?\"",
          "overLyric": true
        }
      ]
    },
    {
      "label": "[HAMILTON]"
    },
    {
      "className": "chordLyricLine",
      "chordLyricPairs": [
        {
          "chord": "Bm",
          "lyric": "Alexander Hamilton",
          "overLyric": true
        }
      ]
    },
    {
      "className": "chordLyricLine",
      "chordLyricPairs": [
        {
          "chord": null,
          "lyric": "My name is ",
          "overLyric": true
        },
        {
          "chord": "F#",
          "lyric": "Alexander Hamilton",
          "overLyric": true
        }
      ]
    },
    {
      "className": "chordLyricLine",
      "chordLyricPairs": [
        {
          "chord": null,
          "lyric": "And there's a ",
          "overLyric": true
        },
        {
          "chord": "G",
          "lyric": "million things I haven't done",
          "overLyric": true
        }
      ]
    },
    {
      "className": "chordLyricLine",
      "chordLyricPairs": [
        {
          "chord": null,
          "lyric": "But just you ",
          "overLyric": true
        },
        {
          "chord": "D",
          "lyric": "wait, just you ",
          "overLyric": true
        },
        {
          "chord": "F#7",
          "lyric": "wait...",
          "overLyric": true
        }
      ]
    },
    {
      "label": "[ELIZA]"
    },
    {
      "className": "chordLyricLine",
      "chordLyricPairs": [
        {
          "chord": null,
          "lyric": "When he was ",
          "overLyric": true
        },
        {
          "chord": "Bm",
          "lyric": "ten his father split, full of it, debt-ridden",
          "overLyric": true
        }
      ]
    },
    {
      "className": "chordLyricLine",
      "chordLyricPairs": [
        {
          "chord": null,
          "lyric": "Two yea",
          "overLyric": true
        },
        {
          "chord": "F#7",
          "lyric": "rs later, see Alex and his mother bed-ridden half-",
          "overLyric": true
        },
        {
          "chord": "G",
          "lyric": "dead",
          "overLyric": true
        }
      ]
    },
    {
      "className": "line",
      "chordLyricPairs": [
        {
          "chord": null,
          "lyric": "Sittin' in their own sick, the scent thick",
          "overLyric": true
        }
      ]
    },
    {
      "label": "[COMPANY]"
    },
    {
      "className": "line",
      "chordLyricPairs": [
        {
          "chord": null,
          "lyric": "And Alex got better but his mother went quick",
          "overLyric": true
        }
      ]
    },
    {
      "label": "[WASHINGTON]"
    },
    {
      "className": "chordLyricLine",
      "chordLyricPairs": [
        {
          "chord": "Bm",
          "lyric": "Moved in with a cousin, the cousin committed suicide",
          "overLyric": true
        }
      ]
    },
    {
      "className": "chordLyricLine",
      "chordLyricPairs": [
        {
          "chord": "F#",
          "lyric": "Left him with nothin' but ruined pride, something new inside",
          "overLyric": true
        }
      ]
    },
    {
      "className": "chordLyricLine",
      "chordLyricPairs": [
        {
          "chord": null,
          "lyric": "A ",
          "overLyric": true
        },
        {
          "chord": "G",
          "lyric": "voice saying",
          "overLyric": true
        }
      ]
    },
    {
      "label": "[WASHINGTON/COMPANY]"
    },
    {
      "className": "line",
      "chordLyricPairs": [
        {
          "chord": null,
          "lyric": "\"You gotta fend for yourself\"  //  \"Alex, you gotta fend for",
          "overLyric": true
        }
      ]
    },
    {
      "className": "line",
      "chordLyricPairs": [
        {
          "chord": null,
          "lyric": "yourself\"",
          "overLyric": true
        }
      ]
    },
    {
      "label": "[WASHINGTON]"
    },
    {
      "className": "chordLyricLine",
      "chordLyricPairs": [
        {
          "chord": null,
          "lyric": "He started ",
          "overLyric": true
        },
        {
          "chord": "D",
          "lyric": "retreatin' and readin' every ",
          "overLyric": true
        },
        {
          "chord": "F#7",
          "lyric": "treatise on the shelf",
          "overLyric": true
        }
      ]
    },
    {
      "label": "[BURR]"
    },
    {
      "className": "chordLyricLine",
      "chordLyricPairs": [
        {
          "chord": null,
          "lyric": "There ",
          "overLyric": true
        },
        {
          "chord": "Bm",
          "lyric": "would have been nothing left to do",
          "overLyric": true
        }
      ]
    },
    {
      "className": "line",
      "chordLyricPairs": [
        {
          "chord": null,
          "lyric": "For someone less astute, he woulda been",
          "overLyric": true
        }
      ]
    },
    {
      "className": "chordLyricLine",
      "chordLyricPairs": [
        {
          "chord": "F#",
          "lyric": "Dead or destitute without a sense of restitution",
          "overLyric": true
        }
      ]
    },
    {
      "className": "chordLyricLine",
      "chordLyricPairs": [
        {
          "chord": null,
          "lyric": "Started ",
          "overLyric": true
        },
        {
          "chord": "G",
          "lyric": "workin', clerkin' for his late mother's landlord",
          "overLyric": true
        }
      ]
    },
    {
      "className": "chordLyricLine",
      "chordLyricPairs": [
        {
          "chord": "D",
          "lyric": "Tradin' sugar cane and rum and ",
          "overLyric": true
        },
        {
          "chord": "F#7",
          "lyric": "all the things he can't afford",
          "overLyric": true
        }
      ]
    },
    {
      "className": "chordLyricLine",
      "chordLyricPairs": [
        {
          "chord": "Bm",
          "lyric": "Scammin' for every book he can get his hands on",
          "overLyric": true
        }
      ]
    },
    {
      "className": "chordLyricLine",
      "chordLyricPairs": [
        {
          "chord": "F#",
          "lyric": "Plannin' for the future see him now as he stands on",
          "overLyric": true
        }
      ]
    },
    {
      "className": "chordLyricLine",
      "chordLyricPairs": [
        {
          "chord": null,
          "lyric": "The ",
          "overLyric": true
        },
        {
          "chord": "G",
          "lyric": "bow of a ship headed for a new land",
          "overLyric": true
        }
      ]
    },
    {
      "className": "chordLyricLine",
      "chordLyricPairs": [
        {
          "chord": null,
          "lyric": "In ",
          "overLyric": true
        },
        {
          "chord": "D",
          "lyric": "New York you can ",
          "overLyric": true
        },
        {
          "chord": "F#7",
          "lyric": "be a new man",
          "overLyric": true
        }
      ]
    },
    {
      "label": "[COMPANY]"
    },
    {
      "className": "chordLyricLine",
      "chordLyricPairs": [
        {
          "chord": null,
          "lyric": "In ",
          "overLyric": true
        },
        {
          "chord": "Bm",
          "lyric": "New York you can   //  (HAMILTON)",
          "overLyric": true
        }
      ]
    },
    {
      "className": "line",
      "chordLyricPairs": [
        {
          "chord": null,
          "lyric": "Be a new man          //  Just you wait",
          "overLyric": true
        }
      ]
    },
    {
      "className": "chordLyricLine",
      "chordLyricPairs": [
        {
          "chord": null,
          "lyric": "In ",
          "overLyric": true
        },
        {
          "chord": "G7",
          "lyric": "New York you can   // (HAMILTON)",
          "overLyric": true
        }
      ]
    },
    {
      "className": "line",
      "chordLyricPairs": [
        {
          "chord": null,
          "lyric": "Be a new man          //  Just you wait",
          "overLyric": true
        }
      ]
    },
    {
      "className": "chordLyricLine",
      "chordLyricPairs": [
        {
          "chord": null,
          "lyric": "In ",
          "overLyric": true
        },
        {
          "chord": "Em7",
          "lyric": "New York you can",
          "overLyric": true
        }
      ]
    },
    {
      "className": "line",
      "chordLyricPairs": [
        {
          "chord": null,
          "lyric": "Be a new man",
          "overLyric": true
        }
      ]
    },
    {
      "label": "[WOMEN]"
    },
    {
      "className": "chordLyricLine",
      "chordLyricPairs": [
        {
          "chord": null,
          "lyric": "In ",
          "overLyric": true
        },
        {
          "chord": "F#7",
          "lyric": "New York--",
          "overLyric": true
        }
      ]
    },
    {
      "label": "[MEN]"
    },
    {
      "className": "line",
      "chordLyricPairs": [
        {
          "chord": null,
          "lyric": "New York",
          "overLyric": true
        }
      ]
    },
    {
      "label": "[HAMILTON]"
    },
    {
      "className": "line",
      "chordLyricPairs": [
        {
          "chord": null,
          "lyric": "Just you wait!",
          "overLyric": true
        }
      ]
    },
    {
      "label": "[COMPANY]"
    },
    {
      "className": "chordLyricLine",
      "chordLyricPairs": [
        {
          "chord": "Bm",
          "lyric": "Alexander Hamilton (Alexander Hamilton)",
          "overLyric": true
        }
      ]
    },
    {
      "className": "chordLyricLine",
      "chordLyricPairs": [
        {
          "chord": null,
          "lyric": "We are ",
          "overLyric": true
        },
        {
          "chord": "G7",
          "lyric": "waiting in the wings for you (waiting in the wings for you)",
          "overLyric": true
        }
      ]
    },
    {
      "className": "chordLyricLine",
      "chordLyricPairs": [
        {
          "chord": null,
          "lyric": "You could ",
          "overLyric": true
        },
        {
          "chord": "Em7",
          "lyric": "never back down",
          "overLyric": true
        }
      ]
    },
    {
      "className": "chordLyricLine",
      "chordLyricPairs": [
        {
          "chord": null,
          "lyric": "You never learned to take your ",
          "overLyric": true
        },
        {
          "chord": "F#7",
          "lyric": "time",
          "overLyric": true
        }
      ]
    },
    {
      "className": "chordLyricLine",
      "chordLyricPairs": [
        {
          "chord": null,
          "lyric": "Oh, ",
          "overLyric": true
        },
        {
          "chord": "Bm",
          "lyric": "Alexander Hamilton (Alexander Hamilton)",
          "overLyric": true
        }
      ]
    },
    {
      "className": "chordLyricLine",
      "chordLyricPairs": [
        {
          "chord": null,
          "lyric": "When A",
          "overLyric": true
        },
        {
          "chord": "G7",
          "lyric": "merica sings for you",
          "overLyric": true
        }
      ]
    },
    {
      "className": "chordLyricLine",
      "chordLyricPairs": [
        {
          "chord": null,
          "lyric": "Will they ",
          "overLyric": true
        },
        {
          "chord": "Em7",
          "lyric": "know what you overcame?",
          "overLyric": true
        }
      ]
    },
    {
      "className": "chordLyricLine",
      "chordLyricPairs": [
        {
          "chord": null,
          "lyric": "Will they ",
          "overLyric": true
        },
        {
          "chord": "Bm",
          "lyric": "know you rewrote the ",
          "overLyric": true
        },
        {
          "chord": "Em",
          "lyric": "game?",
          "overLyric": true
        }
      ]
    },
    {
      "className": "chordLyricLine",
      "chordLyricPairs": [
        {
          "chord": null,
          "lyric": "The ",
          "overLyric": true
        },
        {
          "chord": "Bm",
          "lyric": "world will ",
          "overLyric": true
        },
        {
          "chord": "Em",
          "lyric": "never be",
          "overLyric": true
        },
        {
          "chord": "D",
          "lyric": " the same, ",
          "overLyric": true
        },
        {
          "chord": "F#7",
          "lyric": "oh",
          "overLyric": true
        }
      ]
    },
    {
      "label": "[BURR]"
    },
    {
      "className": "chordLyricLine",
      "chordLyricPairs": [
        {
          "chord": null,
          "lyric": "The ",
          "overLyric": true
        },
        {
          "chord": "Bm",
          "lyric": "ship is in the harbor now  //  (COMPANY)",
          "overLyric": true
        }
      ]
    },
    {
      "className": "line",
      "chordLyricPairs": [
        {
          "chord": null,
          "lyric": "See if you can spot him        //  Just you wait",
          "overLyric": true
        }
      ]
    },
    {
      "className": "line",
      "chordLyricPairs": [
        {
          "chord": null,
          "lyric": "Another immigrant",
          "overLyric": true
        }
      ]
    },
    {
      "className": "chordLyricLine",
      "chordLyricPairs": [
        {
          "chord": null,
          "lyric": "Com",
          "overLyric": true
        },
        {
          "chord": "Em7",
          "lyric": "in' up from the bottom      //  Just you wait",
          "overLyric": true
        }
      ]
    },
    {
      "className": "chordLyricLine",
      "chordLyricPairs": [
        {
          "chord": null,
          "lyric": "His ",
          "overLyric": true
        },
        {
          "chord": "Em",
          "lyric": "enemies destroyed his rep",
          "overLyric": true
        }
      ]
    },
    {
      "className": "line",
      "chordLyricPairs": [
        {
          "chord": null,
          "lyric": "America forgot him",
          "overLyric": true
        }
      ]
    },
    {
      "label": "[MULLIGAN/MADISON & LAFAYETTE/JEFFERSON]"
    },
    {
      "className": "chordLyricLine",
      "chordLyricPairs": [
        {
          "chord": "F#7",
          "lyric": "We fought with him",
          "overLyric": true
        }
      ]
    },
    {
      "label": "[LAURENS/PHILLIP]"
    },
    {
      "className": "line",
      "chordLyricPairs": [
        {
          "chord": null,
          "lyric": "Me? I died for him",
          "overLyric": true
        }
      ]
    },
    {
      "label": "[WASHINGTON]"
    },
    {
      "className": "chordLyricLine",
      "chordLyricPairs": [
        {
          "chord": "Bm",
          "lyric": "Me? I trusted ",
          "overLyric": true
        },
        {
          "chord": "F#",
          "lyric": "him",
          "overLyric": true
        }
      ]
    },
    {
      "label": "[ELIZA & ANGELICA & PEGGY/MARIA]"
    },
    {
      "className": "chordLyricLine",
      "chordLyricPairs": [
        {
          "chord": "Em",
          "lyric": "Me? I loved him",
          "overLyric": true
        }
      ]
    },
    {
      "label": "[BURR]"
    },
    {
      "className": "chordLyricLine",
      "chordLyricPairs": [
        {
          "chord": null,
          "lyric": "And ",
          "overLyric": true
        },
        {
          "chord": "F#",
          "lyric": "me? I'm the damn fool that shot him",
          "overLyric": true
        }
      ]
    },
    {
      "label": "[COMPANY]"
    },
    {
      "className": "chordLyricLine",
      "chordLyricPairs": [
        {
          "chord": null,
          "lyric": "There's a ",
          "overLyric": true
        },
        {
          "chord": "Em",
          "lyric": "million things I haven't done ",
          "overLyric": true
        },
        {
          "chord": "D",
          "lyric": ""
        }
      ]
    },
    {
      "className": "chordLyricLine",
      "chordLyricPairs": [
        {
          "chord": null,
          "lyric": "But just you ",
          "overLyric": true
        },
        {
          "chord": "Em6",
          "lyric": "wait!",
          "overLyric": true
        }
      ]
    },
    {
      "label": "[BURR]"
    },
    {
      "className": "chordLyricLine",
      "chordLyricPairs": [
        {
          "chord": "F#7",
          "lyric": "What's your name, man?",
          "overLyric": true
        }
      ]
    },
    {
      "label": "[COMPANY]"
    },
    {
      "className": "chordLyricLine",
      "chordLyricPairs": [
        {
          "chord": null,
          "lyric": "Alexander Hamilton! ",
          "overLyric": true
        },
        {
          "chord": "Bm",
          "lyric": ""
        }
      ]
    }
  ],
  "title": "Alexander Hamilton",
  "url": "/song/hamilton/alexander_hamilton"
}