{
  "allChords": [
    "Am",
    "E7",
    "F",
    "C",
    "G",
    "D7",
    "Dm",
    "A7"
  ],
  "artist": "Sara Bareilles",
  "fullName": "Bottle It Up - Sara Bareilles",
  "id": "bottle_it_up - sara_bareilles",
  "lines": [
    {
      "chord": "            Am",
      "lyrics": "There'll be girls across the nation"
    },
    {
      "chord": "          E7",
      "lyrics": "That will eat this up babe"
    },
    {
      "chord": "  F                                      C         G",
      "lyrics": "I know that it's your soul but could you bottle it up and"
    },
    {
      "chord": "    Am",
      "lyrics": "Get down to the heart of it,"
    },
    {
      "chord": "E7                           F",
      "lyrics": "No it's my heart you're xxxx out of your luck"
    },
    {
      "chord": "              C         G       Am               E7",
      "lyrics": "Don't make me tell you again my love love love love."
    },
    {
      "chord": "F                C   G",
      "lyrics": "Love love love love."
    },
    {
      "chord": "    Am                          E7",
      "lyrics": "I am aiming to be somebody this somebody trusts"
    },
    {
      "chord": "         F",
      "lyrics": "With her delicate soul"
    },
    {
      "chord": "        C             G           Am",
      "lyrics": "I don't claim to know much except soon as you start"
    },
    {
      "chord": "        E7",
      "lyrics": "To make room for the parts"
    },
    {
      "chord": "            F                     C          G",
      "lyrics": "That aren't you it gets harder to bloom in a garden of"
    },
    {
      "chord": "Am              E7",
      "lyrics": "Love love love love"
    },
    {
      "chord": "F               C       G",
      "lyrics": "Love love love love"
    },
    {
      "chord": "Am          E7                    G",
      "lyrics": "Only thing I ever could need, only one good thing"
    },
    {
      "chord": "      F",
      "lyrics": "Worth trying to be and it's"
    },
    {
      "label": "[Chorus]"
    },
    {
      "chord": "C     G     Am    F",
      "lyrics": "Love, love, love, love"
    },
    {
      "chord": "            C     G     Am    F",
      "lyrics": "I do it for love, love, love, love"
    },
    {
      "chord": "      Am                              E7",
      "lyrics": "We can understand the sentiment you're saying to us"
    },
    {
      "chord": "        F                           C           G",
      "lyrics": "Oh, but sensible sells so could you kindly shut up"
    },
    {
      "chord": "        Am",
      "lyrics": "And get started at keeping"
    },
    {
      "chord": "     E7                       F",
      "lyrics": "Your part of the bargain, oh, please little darlin'"
    },
    {
      "chord": "       C          G            Am              E7",
      "lyrics": "You're killing me sweetly with love love love love"
    },
    {
      "chord": "F               C",
      "lyrics": "Love love love love"
    },
    {
      "label": "[Pre-Chorus]"
    },
    {
      "chord": "Am          E7                    G",
      "lyrics": "Only thing I ever could need, only one good thing"
    },
    {
      "chord": "      F",
      "lyrics": "Worth trying to be and it's"
    },
    {
      "label": "[Chorus]"
    },
    {
      "chord": "C     G     Am    F",
      "lyrics": "Love, love, love, love"
    },
    {
      "chord": "            C     G     Am    F",
      "lyrics": "I do it for love, love, love, love"
    },
    {
      "label": "[Bridge]"
    },
    {
      "chord": "             Am                   E7",
      "lyrics": "Started as a flicker meant to be a flame"
    },
    {
      "chord": "                       G                D7",
      "lyrics": "Skin has gotten thicker but it burns the same"
    },
    {
      "chord": "                  Dm                   A7",
      "lyrics": "Still a baby in a cradle got to take my first fall"
    },
    {
      "chord": "                       C",
      "lyrics": "Baby's getting next to nowhere with her back"
    },
    {
      "chord": " G",
      "lyrics": "Against the wall."
    },
    {
      "chord": "                     Am           E7",
      "lyrics": "You meant to make me happy make me sad."
    },
    {
      "chord": "                       G        D7",
      "lyrics": "Want to make it better better so bad."
    },
    {
      "chord": "                  Dm              A7",
      "lyrics": "But save your resolutions for your never new year"
    },
    {
      "chord": "                    C                G",
      "lyrics": "There is only one solution I can see here."
    },
    {
      "chord": "Am              E7                     G",
      "lyrics": "Love you're all I ever could need only one good thing"
    },
    {
      "chord": "      F",
      "lyrics": "Worth trying to be and it's"
    },
    {
      "label": "[Chorus]"
    },
    {
      "chord": "C     G     Am    F",
      "lyrics": "Love, love, love, love"
    },
    {
      "chord": "            C     G     Am    F",
      "lyrics": "I do it for love, love, love, love"
    },
    {
      "chord": "   C               G                  Am    F",
      "lyrics": "Oh, only gonna get get what you give away,"
    },
    {
      "chord": "C                G                  Am   F",
      "lyrics": "Only gonna get get what you give away...love."
    }
  ],
  "title": "Bottle It Up"
}