{"allChords": ["Em", "C", "Dm", "Bb", "G", "F", "Cm", "Am", "Eb", "Ab", "Gm", "Fm"], "artist": "Disney", "lines": [{"label": "[Rapunzel]"}, {"count": 0, "chord": "C", "lyrics": "All those days"}, {"count": 1, "chord": "G                 C", "lyrics": "Watching from the windows"}, {"count": 2, "chord": "C", "lyrics": "All those years"}, {"count": 3, "chord": "G               C", "lyrics": "Outside looking in"}, {"count": 4, "chord": "F", "lyrics": "All that time"}, {"count": 5, "chord": "C          G", "lyrics": "Never even knowing"}, {"count": 6, "chord": "C        Am         G", "lyrics": "Just how blind I've been"}, {"count": 7, "chord": "C", "lyrics": "Now I'm here"}, {"count": 8, "chord": "G               C", "lyrics": "Blinking in the starlight"}, {"count": 9, "chord": "C", "lyrics": "Now I'm here"}, {"count": 10, "chord": "G          C", "lyrics": "Suddenly I see"}, {"count": 11, "chord": "F", "lyrics": "Standing here"}, {"count": 12, "chord": "     Em", "lyrics": "It's oh, so clear"}, {"count": 13, "chord": "    Dm                 G", "lyrics": "I'm where I'm meant to be"}, {"count": 14, "chord": "       F               C", "lyrics": "And at last, I see the light"}, {"count": 15, "chord": "         G                C", "lyrics": "And it's like the fog has lifted"}, {"count": 16, "chord": "       F               C", "lyrics": "And at last, I see the light"}, {"count": 17, "chord": "         Em              Am", "lyrics": "And it's like the sky is new"}, {"count": 18, "chord": "         F                 C", "lyrics": "And it's warm and real and bright"}, {"count": 19, "chord": "        Em                F", "lyrics": "And the world has somehow shifted"}, {"count": 20, "chord": "C", "lyrics": "All at once"}, {"count": 21, "chord": "G                C", "lyrics": "Everything looks different"}, {"count": 22, "chord": "F        G     C", "lyrics": "Now that I see you"}, {"label": "[Flynn]"}, {"count": 23, "chord": "Eb", "lyrics": "All those days"}, {"count": 24, "chord": "Bb             Eb", "lyrics": "Chasing down a daydream"}, {"count": 25, "chord": "Eb", "lyrics": "All those years"}, {"count": 26, "chord": "Bb          Eb", "lyrics": "Living in a blur"}, {"count": 27, "chord": "Ab", "lyrics": "All that time"}, {"count": 28, "chord": "Eb          Bb", "lyrics": "Never truly seeing"}, {"count": 29, "chord": "Eb                  Bb", "lyrics": "Things the way they were"}, {"count": 30, "chord": "Eb", "lyrics": "Now she's here"}, {"count": 31, "chord": "Bb             Eb", "lyrics": "Shining in the starlight"}, {"count": 32, "chord": "Eb", "lyrics": "Now she's here"}, {"count": 33, "chord": "Bb         Eb", "lyrics": "Suddenly I know"}, {"count": 34, "chord": "Ab", "lyrics": "If she's here"}, {"count": 35, "chord": "     Gm", "lyrics": "It's crystal clear"}, {"count": 36, "chord": "    Fm                 Bb", "lyrics": "I'm where I'm meant to go"}, {"label": "[Flynn/Rapunzel]"}, {"count": 37, "chord": "       Ab              Eb", "lyrics": "And at last, I see the light"}, {"label": "[Flynn]"}, {"count": 38, "chord": "         Bb               Eb", "lyrics": "And it's like the fog has lifted"}, {"label": "[Flynn/Rapunzel]"}, {"count": 39, "chord": "       Ab              Eb", "lyrics": "And at last, I see the light"}, {"label": "[Rapunzel]"}, {"count": 40, "chord": "         Gm              Cm", "lyrics": "And it's like the sky is new"}, {"label": "[Flynn/Rapunzel]"}, {"count": 41, "chord": "         Ab                Eb", "lyrics": "And it's warm and real and bright"}, {"count": 42, "chord": "        Bb                Ab", "lyrics": "And the world has somehow shifted"}, {"count": 43, "chord": "Eb", "lyrics": "All at once"}, {"count": 44, "chord": "Bb            Eb", "lyrics": "Everything is different"}, {"count": 45, "chord": "Ab       Bb    Eb", "lyrics": "Now that I see you"}, {"count": 46, "chord": "Ab       Bb    Eb", "lyrics": "Now that I see you.."}], "id": "I See the Light - Disney", "title": "I See the Light"}