{
  "allChords": [
    "Gm", 
    "Eb", 
    "F", 
    "Bb", 
    "Dm", 
    "Cm"
  ], 
  "artist": "Dido", 
  "id": "Thank You - Dido", 
  "lines": [
    {
      "chord": "Gm            Eb                   F         Bb      F      Gm", 
      "lyrics": "My tea's gone cold, I'm wondering why I got out of bed at all"
    }, 
    {
      "chord": "            Eb                  F           Bb       F      Gm", 
      "lyrics": "The morning rain cloud's up my window, and I can't see at all"
    }, 
    {
      "chord": "         Eb                F                     Bb       F     Gm", 
      "lyrics": "And even if I could, it'd all be gray, but your picture on my wall"
    }, 
    {
      "chord": "     Eb                  Gm                 Eb", 
      "lyrics": "It reminds me that it's not so bad, it's not so bad"
    }, 
    {
      "chord": "  Gm         Eb                    F                Bb         F        Gm", 
      "lyrics": "I drank too much last night, got bills to pay, my head just feels in pain"
    }, 
    {
      "chord": "              Eb                  F                Bb       F      Gm", 
      "lyrics": "I missed the bus and there'll be hell today, I'm late for work again"
    }, 
    {
      "chord": "         Eb                     F                 Bb        F        Gm", 
      "lyrics": "And even if I'm there they'll all imply that I might not last the day"
    }, 
    {
      "chord": "               Eb              Gm                 Eb", 
      "lyrics": "And then you call me and it's not so bad, it's not so bad"
    }, 
    {
      "chord": "    Bb           Eb", 
      "lyrics": "And I want to thank you"
    }, 
    {
      "chord": "                   Bb              Eb", 
      "lyrics": "For giving me the best day of my life"
    }, 
    {
      "chord": "    Bb           Eb", 
      "lyrics": "And oh, just to be with you"
    }, 
    {
      "chord": "              Dm              Cm", 
      "lyrics": "Is having the best day of my life"
    }, 
    {
      "chord": "Bb                  Bb        Eb                    Bb             Bb", 
      "lyrics": "Push the door, I'm home at last and I'm soaking through and through"
    }, 
    {
      "chord": "                Bb     Eb              Bb       Bb", 
      "lyrics": "Then you handed me a towel and all I see is you"
    }, 
    {
      "chord": "                      Bb     Eb                           Dm", 
      "lyrics": "And even if my house falls down now, I wouldn't have a clue"
    }, 
    {
      "chord": "                Cm", 
      "lyrics": "Because you're near me..."
    }, 
    {
      "chord": "    Bb           Eb", 
      "lyrics": "And I want to thank you"
    }, 
    {
      "chord": "                   Bb              Eb", 
      "lyrics": "For giving me the best day of my life"
    }, 
    {
      "chord": "    Bb           Eb", 
      "lyrics": "And oh, just to be with you"
    }, 
    {
      "chord": "              Dm              Cm", 
      "lyrics": "Is having the best day of my life"
    }, 
    {
      "chord": "    Bb           Eb", 
      "lyrics": "And I want to thank you"
    }, 
    {
      "chord": "                   Bb              Eb", 
      "lyrics": "For giving me the best day of my life"
    }, 
    {
      "chord": "    Bb           Eb", 
      "lyrics": "And oh, just to be with you"
    }, 
    {
      "chord": "              Dm              Cm", 
      "lyrics": "Is having the best day of my life"
    }
  ], 
  "title": "Thank You"
}