{
  "allChords": [
    "G",
    "D",
    "C",
    "Am",
    "B",
    "Em"
  ],
  "artist": "Alison Krauss",
  "fullName": "The Lucky One - Alison Krauss",
  "id": "the_lucky_one - alison_krauss",
  "lines": [
    {
      "label": "[Verse]"
    },
    {
      "chord": "     G",
      "lyrics": "You're the lucky one so Ive been told"
    },
    {
      "chord": "    D",
      "lyrics": "As free as the wind blowin' down the road"
    },
    {
      "chord": "    G",
      "lyrics": "Loved by many hated by none"
    },
    {
      "chord": "    C",
      "lyrics": "Id say you were lucky cause you know what you've done"
    },
    {
      "chord": "       G",
      "lyrics": "Not a care in the world not a worry in sight"
    },
    {
      "chord": "  D",
      "lyrics": "Everythings gonna be alright"
    },
    {
      "chord": "               C        G",
      "lyrics": "Cause you're the lucky one"
    },
    {
      "label": "[Verse]"
    },
    {
      "chord": "    G",
      "lyrics": "You're the lucky one always havin' fun"
    },
    {
      "chord": "   D",
      "lyrics": "A jack of all trades, a master of none"
    },
    {
      "chord": "     G",
      "lyrics": "You look at the world with a smilin' eye"
    },
    {
      "chord": "    C",
      "lyrics": "And laugh at the devil as his train rolls by"
    },
    {
      "chord": "   G",
      "lyrics": "Give you a song and a one-night stand"
    },
    {
      "chord": "   D",
      "lyrics": "And you'll be lookin at a happy man"
    },
    {
      "chord": "                  C     G",
      "lyrics": "Cause you're the lucky one"
    },
    {
      "label": "[Chorus]"
    },
    {
      "chord": "             Am",
      "lyrics": "Well you're blessed I guess"
    },
    {
      "chord": "          D",
      "lyrics": "By never knowin' which road you're choosin'"
    },
    {
      "chord": "           Am",
      "lyrics": "To you the next best thing"
    },
    {
      "chord": "                D          B          Em",
      "lyrics": "To playin' and winnin' is playin and losin'"
    },
    {
      "label": "[Verse]"
    },
    {
      "chord": "    G",
      "lyrics": "You're the lucky one I know that now"
    },
    {
      "chord": "      D",
      "lyrics": "Don't ask you why when where or how"
    },
    {
      "chord": "    G",
      "lyrics": "You look at the world through your smilin' eye"
    },
    {
      "chord": "     C",
      "lyrics": "And laugh at the devil as the train goes by"
    },
    {
      "chord": " G",
      "lyrics": "Give you a song and a one-night stand"
    },
    {
      "chord": "  D",
      "lyrics": "And you'll be lookin' at a happy man"
    },
    {
      "chord": "                 C      G",
      "lyrics": "Cause you're the lucky one"
    },
    {
      "label": "[Chorus]"
    },
    {
      "chord": "            Am",
      "lyrics": "Well you're blessed I guess,"
    },
    {
      "chord": "           D",
      "lyrics": "By never knowin' which road you're choosin'"
    },
    {
      "chord": "           Am                              D",
      "lyrics": "To you the next best thing to playin' and winnin'"
    },
    {
      "chord": "    B           Em",
      "lyrics": "Is playin' and losin'"
    },
    {
      "label": "[Verse]"
    },
    {
      "chord": "           G",
      "lyrics": "You're the lucky one I know that now"
    },
    {
      "chord": "      D",
      "lyrics": "Don't ask you why when where or how"
    },
    {
      "chord": "            G",
      "lyrics": "No matter where you're at that's where you'll be"
    },
    {
      "chord": "        C",
      "lyrics": "You can bet your luck won't follow me"
    },
    {
      "chord": "  G",
      "lyrics": "Give you a song and a one-night stand"
    },
    {
      "chord": "     D",
      "lyrics": "And you'll be lookin' at a happy man"
    },
    {
      "chord": "            C         G",
      "lyrics": "Cause you're the lucky one"
    }
  ],
  "title": "The Lucky One"
}