{
  "allChords": [
    "C",
    "Em",
    "F",
    "Am",
    "G"
  ],
  "artist": "CHVRCHES",
  "capo": "1",
  "fullName": "The Mother We Share - CHVRCHES",
  "id": "the_mother_we_share - chvrches",
  "lines": [
    {
      "label": "[Intro]"
    },
    {
      "chord": "C     Em     F",
      "lyrics": ""
    },
    {
      "label": "[Verse]"
    },
    {
      "chord": "      Am                    G               C",
      "lyrics": "Never took your side, never cursed your name;"
    },
    {
      "chord": "           F                           G",
      "lyrics": "I keep my lips shut tight until you go."
    },
    {
      "chord": "      Am                   G",
      "lyrics": "We've come as far as we're ever gonna get"
    },
    {
      "chord": "           F",
      "lyrics": "until you realize that you should go."
    },
    {
      "label": "[Chorus]"
    },
    {
      "chord": "        C                          Em",
      "lyrics": "I'm in misery where you can seem as old as your omens,"
    },
    {
      "chord": "         F",
      "lyrics": "and the mother we share will never keep your proud head from falling."
    },
    {
      "chord": "     C                               Em",
      "lyrics": "The way is long, but you can make it easy on me,"
    },
    {
      "chord": "         F",
      "lyrics": "and the mother we share will never keep our cold hearts from calling."
    },
    {
      "label": "[Verse]"
    },
    {
      "chord": "       Am                     G            C",
      "lyrics": "In the dead of night, I'm the only one here"
    },
    {
      "chord": "            F                     G",
      "lyrics": "and I will cover you until you go;"
    },
    {
      "chord": "            Am                     G",
      "lyrics": "'cause if I told the truth, I will always be free"
    },
    {
      "chord": "            F",
      "lyrics": "and keep a prize with me until you go."
    },
    {
      "label": "[Chorus]"
    },
    {
      "chord": "        C                          Em",
      "lyrics": "I'm in misery where you can seem as old as your omens,"
    },
    {
      "chord": "         F",
      "lyrics": "and the mother we share will never keep your proud head from falling."
    },
    {
      "chord": "     C                               Em",
      "lyrics": "The way is long, but you can make it easy on me,"
    },
    {
      "chord": "         F",
      "lyrics": "and the mother we share will never keep our cold hearts from calling."
    },
    {
      "chord": "Am     G     F",
      "lyrics": ""
    },
    {
      "label": "[Verse]"
    },
    {
      "chord": "          Am                        Em",
      "lyrics": "Into the night, for once, we're the only ones left."
    },
    {
      "chord": "           F",
      "lyrics": "I bet you even know where we could go."
    },
    {
      "chord": "            Am                         Em",
      "lyrics": "And when it all fucks up, you put your head in my hands;"
    },
    {
      "chord": "        F",
      "lyrics": "it's a souvenir for when you go."
    },
    {
      "label": "[Chorus]"
    },
    {
      "chord": "        C                          Em",
      "lyrics": "I'm in misery where you can seem as old as your omens,"
    },
    {
      "chord": "         F",
      "lyrics": "and the mother we share will never keep your proud head from falling."
    },
    {
      "chord": "     C                               Em",
      "lyrics": "The way is long, but you can make it easy on me,"
    },
    {
      "chord": "         F",
      "lyrics": "and the mother we share will never keep our cold hearts from calling."
    }
  ],
  "title": "The Mother We Share"
}