{
  "allChords": [
    "Bb",
    "Bbsus4",
    "Eb",
    "F",
    "Gm"
  ],
  "artist": "Carly Rae Jepsen",
  "fullName": "Want You In My Room - Carly Rae Jepsen",
  "songId": "want_you_in_my_room - carly_rae_jepsen",
  "lines": [
    {
      "label": "[Verse 1]"
    },
    {
      "className": "chordLyricLine",
      "chordLyricPairs": [
        {
          "chord": null,
          "lyric": "A|",
          "overLyric": true
        },
        {
          "chord": "Bb",
          "lyric": "------------",
          "overLyric": true
        },
        {
          "chord": "Bbsus4",
          "lyric": "------------",
          "overLyric": true
        }
      ]
    },
    {
      "className": "line",
      "chordLyricPairs": [
        {
          "chord": null,
          "lyric": "E|--1--1---1----1--1---1--",
          "overLyric": true
        }
      ]
    },
    {
      "className": "line",
      "chordLyricPairs": [
        {
          "chord": null,
          "lyric": "C|-2-2--2-2-2--3-3--3-3-3-",
          "overLyric": true
        }
      ]
    },
    {
      "className": "line",
      "chordLyricPairs": [
        {
          "chord": null,
          "lyric": "G|3-----------3-----------",
          "overLyric": true
        }
      ]
    },
    {
      "className": "chordLyricLine",
      "chordLyricPairs": [
        {
          "chord": null,
          "lyric": "When all the ",
          "overLyric": true
        },
        {
          "chord": "Bb",
          "lyric": "lights out (Hey), where you going",
          "overLyric": true
        },
        {
          "chord": "Bbsus4",
          "lyric": "?",
          "overLyric": true
        }
      ]
    },
    {
      "className": "chordLyricLine",
      "chordLyricPairs": [
        {
          "chord": null,
          "lyric": "I keep a ",
          "overLyric": true
        },
        {
          "chord": "Bb",
          "lyric": "window, for you, it's always open",
          "overLyric": true
        },
        {
          "chord": "Bbsus4",
          "lyric": ""
        }
      ]
    },
    {
      "className": "chordLyricLine",
      "chordLyricPairs": [
        {
          "chord": null,
          "lyric": "I'm like a ",
          "overLyric": true
        },
        {
          "chord": "Bb",
          "lyric": "lighthouse, I'm a reminder of ",
          "overLyric": true
        },
        {
          "chord": "Bbsus4",
          "lyric": "where you going",
          "overLyric": true
        }
      ]
    },
    {
      "className": "chordLyricLine",
      "chordLyricPairs": [
        {
          "chord": null,
          "lyric": "I'm in your ",
          "overLyric": true
        },
        {
          "chord": "Bb",
          "lyric": "head now, from every second now",
          "overLyric": true
        }
      ]
    },
    {
      "className": "chordLyricLine",
      "chordLyricPairs": [
        {
          "chord": null,
          "lyric": "Is your ",
          "overLyric": true
        },
        {
          "chord": "Bbsus4",
          "lyric": "love growing?",
          "overLyric": true
        }
      ]
    },
    {
      "label": "[Pre-Chorus]"
    },
    {
      "className": "chordLyricLine",
      "chordLyricPairs": [
        {
          "chord": null,
          "lyric": "Oh, with ",
          "overLyric": true
        },
        {
          "chord": "Eb",
          "lyric": "you (Hey), a ",
          "overLyric": true
        },
        {
          "chord": "Bb",
          "lyric": "girl could get bolder",
          "overLyric": true
        }
      ]
    },
    {
      "className": "chordLyricLine",
      "chordLyricPairs": [
        {
          "chord": "F",
          "lyric": " I just wanna get a ",
          "overLyric": true
        },
        {
          "chord": "Gm",
          "lyric": "little bit closer (",
          "overLyric": true
        },
        {
          "chord": "Eb",
          "lyric": "Ha-ah-ah)",
          "overLyric": true
        }
      ]
    },
    {
      "className": "chordLyricLine",
      "chordLyricPairs": [
        {
          "chord": null,
          "lyric": "And I'll ",
          "overLyric": true
        },
        {
          "chord": "Bb",
          "lyric": "press you to the ",
          "overLyric": true
        },
        {
          "chord": "F",
          "lyric": "pages of my ",
          "overLyric": true
        },
        {
          "chord": "Gm",
          "lyric": "heart",
          "overLyric": true
        }
      ]
    },
    {
      "className": "chordLyricLine",
      "chordLyricPairs": [
        {
          "chord": null,
          "lyric": "Don't ",
          "overLyric": true
        },
        {
          "chord": "Eb",
          "lyric": "go, no (Hey), the ",
          "overLyric": true
        },
        {
          "chord": "Bb",
          "lyric": "night's not over",
          "overLyric": true
        }
      ]
    },
    {
      "className": "chordLyricLine",
      "chordLyricPairs": [
        {
          "chord": "F",
          "lyric": " I just wanna get a ",
          "overLyric": true
        },
        {
          "chord": "Gm",
          "lyric": "little bit closer (A little bit ",
          "overLyric": true
        },
        {
          "chord": "Eb",
          "lyric": "closer)",
          "overLyric": true
        }
      ]
    },
    {
      "className": "chordLyricLine",
      "chordLyricPairs": [
        {
          "chord": null,
          "lyric": "And I'll ",
          "overLyric": true
        },
        {
          "chord": "Bb",
          "lyric": "press you to the ",
          "overLyric": true
        },
        {
          "chord": "F",
          "lyric": "pages of my ",
          "overLyric": true
        },
        {
          "chord": "Gm",
          "lyric": "heart (Hey)",
          "overLyric": true
        }
      ]
    },
    {
      "label": "[Chorus]"
    },
    {
      "className": "chordLyricLine",
      "chordLyricPairs": [
        {
          "chord": null,
          "lyric": "(I ",
          "overLyric": true
        },
        {
          "chord": "Eb",
          "lyric": "want you in my ",
          "overLyric": true
        },
        {
          "chord": "Bb",
          "lyric": "room)",
          "overLyric": true
        }
      ]
    },
    {
      "className": "chordLyricLine",
      "chordLyricPairs": [
        {
          "chord": null,
          "lyric": "On the ",
          "overLyric": true
        },
        {
          "chord": "F",
          "lyric": "bed, on the ",
          "overLyric": true
        },
        {
          "chord": "Gm",
          "lyric": "floor",
          "overLyric": true
        }
      ]
    },
    {
      "className": "chordLyricLine",
      "chordLyricPairs": [
        {
          "chord": null,
          "lyric": "(I ",
          "overLyric": true
        },
        {
          "chord": "Eb",
          "lyric": "want you in my ",
          "overLyric": true
        },
        {
          "chord": "Bb",
          "lyric": "room)",
          "overLyric": true
        }
      ]
    },
    {
      "className": "chordLyricLine",
      "chordLyricPairs": [
        {
          "chord": "F",
          "lyric": "I don't care any",
          "overLyric": true
        },
        {
          "chord": "Gm",
          "lyric": "more",
          "overLyric": true
        }
      ]
    },
    {
      "className": "chordLyricLine",
      "chordLyricPairs": [
        {
          "chord": null,
          "lyric": "I wanna ",
          "overLyric": true
        },
        {
          "chord": "Eb",
          "lyric": "do bad things to ",
          "overLyric": true
        },
        {
          "chord": "Bb",
          "lyric": "you",
          "overLyric": true
        }
      ]
    },
    {
      "className": "chordLyricLine",
      "chordLyricPairs": [
        {
          "chord": "F",
          "lyric": "Slide on through my ",
          "overLyric": true
        },
        {
          "chord": "Gm",
          "lyric": "window",
          "overLyric": true
        }
      ]
    },
    {
      "className": "chordLyricLine",
      "chordLyricPairs": [
        {
          "chord": null,
          "lyric": "(I ",
          "overLyric": true
        },
        {
          "chord": "Eb",
          "lyric": "want you in my ",
          "overLyric": true
        },
        {
          "chord": "Bb",
          "lyric": "room)",
          "overLyric": true
        }
      ]
    },
    {
      "className": "chordLyricLine",
      "chordLyricPairs": [
        {
          "chord": "F",
          "lyric": "Baby, don't you want me, ",
          "overLyric": true
        },
        {
          "chord": "Gm",
          "lyric": "too?",
          "overLyric": true
        }
      ]
    },
    {
      "label": "[Verse 2]"
    },
    {
      "className": "chordLyricLine",
      "chordLyricPairs": [
        {
          "chord": null,
          "lyric": "When no one ",
          "overLyric": true
        },
        {
          "chord": "Bb",
          "lyric": "loves you like they really mean it ",
          "overLyric": true
        },
        {
          "chord": "Bbsus4",
          "lyric": ""
        }
      ]
    },
    {
      "className": "chordLyricLine",
      "chordLyricPairs": [
        {
          "chord": null,
          "lyric": "I got you ",
          "overLyric": true
        },
        {
          "chord": "Bb",
          "lyric": "covered, under covers",
          "overLyric": true
        }
      ]
    },
    {
      "className": "chordLyricLine",
      "chordLyricPairs": [
        {
          "chord": "Bbsus4",
          "lyric": " Can you feel it?",
          "overLyric": true
        }
      ]
    },
    {
      "label": "[Pre-Chorus]"
    },
    {
      "className": "chordLyricLine",
      "chordLyricPairs": [
        {
          "chord": null,
          "lyric": "Oh, with ",
          "overLyric": true
        },
        {
          "chord": "Eb",
          "lyric": "you (Hey), a ",
          "overLyric": true
        },
        {
          "chord": "Bb",
          "lyric": "girl could get bolder",
          "overLyric": true
        }
      ]
    },
    {
      "className": "chordLyricLine",
      "chordLyricPairs": [
        {
          "chord": "F",
          "lyric": " I just wanna get a ",
          "overLyric": true
        },
        {
          "chord": "Gm",
          "lyric": "little bit closer (",
          "overLyric": true
        },
        {
          "chord": "Eb",
          "lyric": "Ha-ah-ah)",
          "overLyric": true
        }
      ]
    },
    {
      "className": "chordLyricLine",
      "chordLyricPairs": [
        {
          "chord": null,
          "lyric": "And I'll ",
          "overLyric": true
        },
        {
          "chord": "Bb",
          "lyric": "press you to the ",
          "overLyric": true
        },
        {
          "chord": "F",
          "lyric": "pages of my ",
          "overLyric": true
        },
        {
          "chord": "Gm",
          "lyric": "heart",
          "overLyric": true
        }
      ]
    },
    {
      "className": "chordLyricLine",
      "chordLyricPairs": [
        {
          "chord": null,
          "lyric": "Don't ",
          "overLyric": true
        },
        {
          "chord": "Eb",
          "lyric": "go, no (Hey), the ",
          "overLyric": true
        },
        {
          "chord": "Bb",
          "lyric": "night's not over",
          "overLyric": true
        }
      ]
    },
    {
      "className": "chordLyricLine",
      "chordLyricPairs": [
        {
          "chord": "F",
          "lyric": " I just wanna get a ",
          "overLyric": true
        },
        {
          "chord": "Gm",
          "lyric": "little bit closer (A little bit ",
          "overLyric": true
        },
        {
          "chord": "Eb",
          "lyric": "closer)",
          "overLyric": true
        }
      ]
    },
    {
      "className": "chordLyricLine",
      "chordLyricPairs": [
        {
          "chord": null,
          "lyric": "And I'll ",
          "overLyric": true
        },
        {
          "chord": "Bb",
          "lyric": "press you to the ",
          "overLyric": true
        },
        {
          "chord": "F",
          "lyric": "pages of my ",
          "overLyric": true
        },
        {
          "chord": "Gm",
          "lyric": "heart (Hey)",
          "overLyric": true
        }
      ]
    },
    {
      "label": "[Chorus]"
    },
    {
      "className": "chordLyricLine",
      "chordLyricPairs": [
        {
          "chord": null,
          "lyric": "(I ",
          "overLyric": true
        },
        {
          "chord": "Eb",
          "lyric": "want you in my ",
          "overLyric": true
        },
        {
          "chord": "Bb",
          "lyric": "room)",
          "overLyric": true
        }
      ]
    },
    {
      "className": "chordLyricLine",
      "chordLyricPairs": [
        {
          "chord": null,
          "lyric": "On the ",
          "overLyric": true
        },
        {
          "chord": "F",
          "lyric": "bed, on the ",
          "overLyric": true
        },
        {
          "chord": "Gm",
          "lyric": "floor",
          "overLyric": true
        }
      ]
    },
    {
      "className": "chordLyricLine",
      "chordLyricPairs": [
        {
          "chord": null,
          "lyric": "(I ",
          "overLyric": true
        },
        {
          "chord": "Eb",
          "lyric": "want you in my ",
          "overLyric": true
        },
        {
          "chord": "Bb",
          "lyric": "room)",
          "overLyric": true
        }
      ]
    },
    {
      "className": "chordLyricLine",
      "chordLyricPairs": [
        {
          "chord": "F",
          "lyric": "I don't care any",
          "overLyric": true
        },
        {
          "chord": "Gm",
          "lyric": "more",
          "overLyric": true
        }
      ]
    },
    {
      "className": "chordLyricLine",
      "chordLyricPairs": [
        {
          "chord": null,
          "lyric": "I wanna ",
          "overLyric": true
        },
        {
          "chord": "Eb",
          "lyric": "do bad things to ",
          "overLyric": true
        },
        {
          "chord": "Bb",
          "lyric": "you",
          "overLyric": true
        }
      ]
    },
    {
      "className": "chordLyricLine",
      "chordLyricPairs": [
        {
          "chord": "F",
          "lyric": "Slide on through my ",
          "overLyric": true
        },
        {
          "chord": "Gm",
          "lyric": "window",
          "overLyric": true
        }
      ]
    },
    {
      "className": "chordLyricLine",
      "chordLyricPairs": [
        {
          "chord": null,
          "lyric": "(I ",
          "overLyric": true
        },
        {
          "chord": "Eb",
          "lyric": "want you in my ",
          "overLyric": true
        },
        {
          "chord": "Bb",
          "lyric": "room)",
          "overLyric": true
        }
      ]
    },
    {
      "className": "chordLyricLine",
      "chordLyricPairs": [
        {
          "chord": "F",
          "lyric": "Baby, don't you want me, ",
          "overLyric": true
        },
        {
          "chord": "Gm",
          "lyric": "too?",
          "overLyric": true
        }
      ]
    },
    {
      "label": "[Outro]"
    },
    {
      "className": "line",
      "chordLyricPairs": [
        {
          "chord": "Eb",
          "lyric": " "
        },
        {
          "chord": "Bb",
          "lyric": " "
        },
        {
          "chord": "F",
          "lyric": " "
        },
        {
          "chord": "Gm",
          "lyric": ""
        }
      ]
    }
  ],
  "title": "Want You In My Room"
}